mcp_server_motherduck/__init__.py
mcp_server_motherduck/configs.py
mcp_server_motherduck/database.py
mcp_server_motherduck/prompt.py
mcp_server_motherduck/server.py
mseep_mcp_server_motherduck-0.6.4.dist-info/licenses/LICENSE
mseep_mcp_server_motherduck-0.6.4.dist-info/METADATA
mseep_mcp_server_motherduck-0.6.4.dist-info/WHEEL
mseep_mcp_server_motherduck-0.6.4.dist-info/entry_points.txt
mseep_mcp_server_motherduck-0.6.4.dist-info/top_level.txt
mseep_mcp_server_motherduck-0.6.4.dist-info/RECORD
