Metadata-Version: 2.4
Name: mseep-mcp-server-motherduck
Version: 0.6.4
Summary: A MCP server for MotherDuck and local DuckDB
Author-email: mseep <support@skydeck.ai>
Requires-Python: >=3.10
License-File: LICENSE
Requires-Dist: duckdb==1.3.1
Requires-Dist: tabulate>=0.9.0
Requires-Dist: click>=8.1.8
Requires-Dist: starlette>=0.46.1
Requires-Dist: uvicorn>=0.34.0
Requires-Dist: anyio>=4.8.0
Requires-Dist: mcp>=1.9.4
Requires-Dist: pytz>=2025.2
Dynamic: license-file
